LICENSE
MANIFEST.in
README.md
setup.py
tubefox/__init__.py
tubefox/app_scraper.py
tubefox/data_collector.py
tubefox/downloader.py
tubefox/helpers.py
tubefox/subtitles.py
tubefox/tubefox.py
tubefox/version.py
tubefox/web_scraper.py
tubefox/yt_app_version_updater.py
tubefox.egg-info/PKG-INFO
tubefox.egg-info/SOURCES.txt
tubefox.egg-info/dependency_links.txt
tubefox.egg-info/requires.txt
tubefox.egg-info/top_level.txt