Metadata-Version: 2.1
Name: tubefox
Version: 0.8.7
Summary: A package for scraping YouTube data
Home-page: https://github.com/FoxPyDev/tubefox
Author: @FoxPyDev Yaroslav Lysenko
Author-email: foxpythondev@gmail.com
Classifier: Programming Language :: Python :: 3
Classifier: License :: OSI Approved :: MIT License
Classifier: Operating System :: OS Independent
Requires-Python: >=3.6
License-File: LICENSE
